aio_geojson_client/__init__.py
aio_geojson_client/consts.py
aio_geojson_client/exceptions.py
aio_geojson_client/feed.py
aio_geojson_client/feed_entry.py
aio_geojson_client/feed_manager.py
aio_geojson_client/filter_definition.py
aio_geojson_client/geojson_distance_helper.py
aio_geojson_client/status_update.py
aio_geojson_client/geometries/__init__.py
aio_geojson_client/geometries/geometry.py
aio_geojson_client/geometries/point.py
aio_geojson_client/geometries/polygon.py
aio_geojson_client-0.21.dist-info/LICENSE
aio_geojson_client-0.21.dist-info/METADATA
aio_geojson_client-0.21.dist-info/WHEEL
aio_geojson_client-0.21.dist-info/top_level.txt
aio_geojson_client-0.21.dist-info/RECORD
